tech_djy_mcp_demo/__init__.py
tech_djy_mcp_demo-0.1.0.dist-info/WHEEL
tech_djy_mcp_demo-0.1.0.dist-info/entry_points.txt
tech_djy_mcp_demo-0.1.0.dist-info/METADATA
tech_djy_mcp_demo-0.1.0.dist-info/RECORD
