Metadata-Version: 2.3
Name: tech-djy-mcp-demo
Version: 0.1.0
Summary: Add your description here
Author: dongchengwei782-dot
Author-email: dongchengwei782-dot <dongchengwei782@gmail.com>
Requires-Dist: mcp[cli]>=1.25.0
Requires-Python: >=3.14
